{
	"$schema": "https://schemas.wp.org/trunk/block.json",
	"apiVersion": 2,
	"name": "wporg/code-reference-user-notes",
	"version": "0.1.0",
	"title": "Code Reference: User Notes",
	"category": "widgets",
	"icon": "smiley",
	"description": "Show the code signature for a function, class, or method.",
	"supports": {
		"html": false,
		"spacing": {
			"margin": [
				"top",
				"bottom"
			],
			"padding": true
		},
		"typography": {
			"fontSize": true,
			"lineHeight": true
		}
	},
	"textdomain": "wporg",
	"editorScript": "file:./index.js",
	"style": "file:./style-index.css"
}
